eclypse/__init__.py
eclypse/builders/__init__.py
eclypse/builders/application/__init__.py
eclypse/builders/application/sock_shop/__init__.py
eclypse/builders/application/sock_shop/application.py
eclypse/builders/application/sock_shop/mpi_services/__init__.py
eclypse/builders/application/sock_shop/mpi_services/cart.py
eclypse/builders/application/sock_shop/mpi_services/catalog.py
eclypse/builders/application/sock_shop/mpi_services/frontend.py
eclypse/builders/application/sock_shop/mpi_services/order.py
eclypse/builders/application/sock_shop/mpi_services/payment.py
eclypse/builders/application/sock_shop/mpi_services/shipping.py
eclypse/builders/application/sock_shop/mpi_services/user.py
eclypse/builders/application/sock_shop/rest_services/__init__.py
eclypse/builders/application/sock_shop/rest_services/cart.py
eclypse/builders/application/sock_shop/rest_services/catalog.py
eclypse/builders/application/sock_shop/rest_services/frontend.py
eclypse/builders/application/sock_shop/rest_services/order.py
eclypse/builders/application/sock_shop/rest_services/payment.py
eclypse/builders/application/sock_shop/rest_services/shipping.py
eclypse/builders/application/sock_shop/rest_services/user.py
eclypse/builders/infrastructure/__init__.py
eclypse/builders/infrastructure/generators/__init__.py
eclypse/builders/infrastructure/generators/b_cube.py
eclypse/builders/infrastructure/generators/fat_tree.py
eclypse/builders/infrastructure/generators/hierarchical.py
eclypse/builders/infrastructure/generators/random.py
eclypse/builders/infrastructure/generators/star.py
eclypse/builders/infrastructure/orion_cev.py
eclypse/graph/__init__.py
eclypse/graph/application.py
eclypse/graph/asset_graph.py
eclypse/graph/assets/__init__.py
eclypse/graph/assets/additive.py
eclypse/graph/assets/asset.py
eclypse/graph/assets/bucket.py
eclypse/graph/assets/concave.py
eclypse/graph/assets/convex.py
eclypse/graph/assets/defaults.py
eclypse/graph/assets/multiplicative.py
eclypse/graph/assets/space.py
eclypse-0.8.2.dist-info/METADATA
eclypse-0.8.2.dist-info/WHEEL
eclypse-0.8.2.dist-info/licenses/LICENSE
eclypse-0.8.2.dist-info/RECORD
