Metadata-Version: 2.4
Name: eclypse
Version: 0.8.2
Summary: an Edge-CLoud pYthon Platform for Simulated runtime Environments
License-File: LICENSE
Author: Jacopo Massa
Author-email: jacopo.massa@di.unipi.it
Maintainer: Jacopo Massa
Maintainer-email: jacopo.massa@di.unipi.it
Requires-Python: >=3.11,<3.14
Classifier: Programming Language :: Python :: 3
Classifier: Programming Language :: Python :: 3.11
Classifier: Programming Language :: Python :: 3.12
Classifier: Programming Language :: Python :: 3.13
Provides-Extra: remote
Provides-Extra: tboard
Requires-Dist: aiofiles (>=25.1.0,<26.0.0)
Requires-Dist: loguru (>=0.7.3,<0.8.0)
Requires-Dist: networkx (>=3.6.1,<4.0.0)
Requires-Dist: ray[default] (>=2.53.0,<3.0.0) ; extra == "remote"
Requires-Dist: tensorboardX (>=2.6.4,<3.0.0) ; extra == "tboard"
Project-URL: Homepage, https://github.com/eclypse-org/eclypse
Project-URL: Repository, https://github.com/eclypse-org/eclypse
